coding_games/ActorState.py
coding_games/AnimatedActor.py
coding_games/Backpack.py
coding_games/Controlable.py
coding_games/Dialog.py
coding_games/Direction.py
coding_games/DizzyActor.py
coding_games/DizzyState.py
coding_games/Flare.py
coding_games/GameState.py
coding_games/Harmfull.py
coding_games/Hud.py
coding_games/Item.py
coding_games/Level.py
coding_games/Settings.py
coding_games/State.py
coding_games/Usable.py
coding_games/__init__.py
coding_games/app.py
coding_games/controller.py
coding_games/examples/games/1. lets_get_moving/fonts/dizzy-iii-fantasy-world-dizzy-spectrum.ttf
coding_games/examples/games/1. lets_get_moving/fonts/license.txt
coding_games/examples/games/1. lets_get_moving/fonts/readme.txt
coding_games/examples/games/1. lets_get_moving/images/animated-flare.png
coding_games/examples/games/1. lets_get_moving/images/bat.png
coding_games/examples/games/1. lets_get_moving/images/boat.png
coding_games/examples/games/1. lets_get_moving/images/cherry.png
coding_games/examples/games/1. lets_get_moving/images/crate.png
coding_games/examples/games/1. lets_get_moving/images/dialog_cross.png
coding_games/examples/games/1. lets_get_moving/images/dialog_end.png
coding_games/examples/games/1. lets_get_moving/images/dialog_middle.png
coding_games/examples/games/1. lets_get_moving/images/dialog_start.png
coding_games/examples/games/1. lets_get_moving/images/dizzy-left-2.png
coding_games/examples/games/1. lets_get_moving/images/dizzy-left.png
coding_games/examples/games/1. lets_get_moving/images/dizzy-right-2.png
coding_games/examples/games/1. lets_get_moving/images/dizzy-right.png
coding_games/examples/games/1. lets_get_moving/images/dizzy-standing-2.png
coding_games/examples/games/1. lets_get_moving/images/dizzy-standing.png
coding_games/examples/games/1. lets_get_moving/images/dizzy_jump-2.png
coding_games/examples/games/1. lets_get_moving/images/dizzy_jump.png
coding_games/examples/games/1. lets_get_moving/images/door.png
coding_games-0.1.7.dist-info/WHEEL
coding_games-0.1.7.dist-info/METADATA
coding_games-0.1.7.dist-info/RECORD
