Metadata-Version: 2.1
Name: coding-games
Version: 0.1.7
Summary: The library to quickly create 2D games based on the game Dizzy - Prince of Yolkfolk.. The documentation can be found here: https://mirka-filcakova.gitbook.io/dizzy/
Author: Gabriel Adamcak
Author-email: adamcakg@gmail.com
Requires-Python: >=3.8,<4.0
Classifier: Programming Language :: Python :: 3
Classifier: Programming Language :: Python :: 3.10
Classifier: Programming Language :: Python :: 3.8
Classifier: Programming Language :: Python :: 3.9
Requires-Dist: PyTMX (>=3.31,<4.0)
Requires-Dist: matches (>=0.0.1,<0.0.2)
Requires-Dist: pgzero (>=1.2.1,<2.0.0)
